neotermcolor/__init__.py
neotermcolor-2.0.11.dist-info/licenses/LICENSE
neotermcolor-2.0.11.dist-info/METADATA
neotermcolor-2.0.11.dist-info/WHEEL
neotermcolor-2.0.11.dist-info/top_level.txt
neotermcolor-2.0.11.dist-info/RECORD
