Metadata-Version: 2.4
Name: neotermcolor
Version: 2.0.11
Summary: Fork of termcolor library
Author-email: Altertech <div@altertech.com>
License-Expression: MIT
Project-URL: Source, https://github.com/alttch/neotermcolor
Project-URL: Issues, https://github.com/alttch/neotermcolor/issues
Classifier: Programming Language :: Python :: 3
Classifier: Topic :: Software Development :: Libraries
Classifier: Topic :: Text Processing
Classifier: Topic :: Terminals
License-File: LICENSE
Dynamic: license-file
